Laboratorio#9/Ej2/Tflop.v
//Jose Luis Alvarez Pineda
//19392
//Seccion 21
//Laboratorio #09, construccion de un FF tipo T utilizando un FF tipo D

module Dflop(
  input wire clk,reset,enable,D,
  output reg Y);

  always @ (posedge clk, posedge reset) begin
    if (reset == 1) Y <= 0;
    else if(enable == 1) Y <= D;
    else Y <= Y;
  end

endmodule

module TFLOP(
  input wire clk,reset,enable,
  output wire Y);

wire Tval;

Dflop Dff(clk,reset,enable,Tval,Y);
assign Tval = enable ^ Y;

endmodule

Laboratorio#9/Ej2/Tflop_tb.v
module testbench();
reg enable,clk,reset;
wire Y;

TFLOP FFT (clk,reset,enable,Y);

initial begin
clk = 0;
forever #1 clk = ~clk;
end

initial begin
reset = 1; enable = 0;
#1 reset = 0;
#5 enable = 1;
#10 enable = 0;
#5 enable = 1;
#2 reset = 1; enable = 0;
#1 reset = 0;
end

initial begin
#100 $finish;
end

initial begin
$dumpfile("Tflop_tb.vcd");
$dumpvars(0, testbench);
end

endmodule

Laboratorio#9/Ej2/Tflop_tb.vcd
$date
	Thu Oct 29 12:27:26 2020
$end
$version
	Icarus Verilog
$end
$timescale
	1ps
$end
$scope module testbench $end
$var wire 1 ! Y $end
$var reg 1 " clk $end
$var reg 1 # enable $end
$var reg 1 $ reset $end
$scope module FFT $end
$var wire 1 % Tval $end
$var wire 1 " clk $end
$var wire 1 # enable $end
$var wire 1 $ reset $end
$var wire 1 ! Y $end
$scope module Dff $end
$var wire 1 % D $end
$var wire 1 " clk $end
$var wire 1 # enable $end
$var wire 1 $ reset $end
$var reg 1 ! Y $end
$upscope $end
$upscope $end
$upscope $end
$enddefinitions $end
#0
$dumpvars
0%
1$
0#
0"
0!
$end
#1
0$
1"
#2
0"
#3
1"
#4
0"
#5
1"
#6
1%
0"
1#
#7
0%
1!
1"
#8
0"
#9
1%
0!
1"
#10
0"
#11
0%
1!
1"
#12
0"
#13
1%
0!
1"
#14
0"
#15
0%
1!
1"
#16
1%
0"
0#
#17
1"
#18
0"
#19
1"
#20
0"
#21
0!
1%
1"
1#
#22
0"
#23
0%
1"
0#
1$
#24
0"
0$
