Laboratorio#6/Ejercicio5/Dflop.v
///////////////////////////////////////////////////////////////////////////////
///Jose Luis Alvarez Pineda
///19392
///Electronica digital
///Laboratorio #06, diseño de flip-flop tipo D con reset asincrono y set sincrono
///////////////////////////////////////////////////////////////////////////////
module Dflop(input logic clk,
  input logic areset,
  input logic[3:0] D,
  output reg[3:0] Y);
//areset es el reset asincrono en el flip flop, no es necesario el clock para cambiar el
//estado
  always @ (posedge clk, posedge areset) begin
      //if para evitar que otro valor pase cuando se active el reset
      if(areset)
      Y <= 4'b0000;
      else
      Y <= D;
  end

endmodule

Laboratorio#6/Ejercicio5/Dflop_tb.v
module testbench();
//variables a utilizar para el flipflop
reg[3:0] D; // ya que no se utilizan valores de asignacion continua
reg clk;    // se asignan como registros
reg reset;
wire[3:0] Y; // cable que si acepta asignacion continua (mantiene el valor de la salida del FF)

Dflop df1(clk, reset, D, Y); //para crear el flip flop

initial begin
//bloque para generar el reloj, inicia en 0 y cada 10 unidades de tiempo
//cambia su estado.
  clk = 0;
      forever #10 clk = ~clk; //corre durante toda la simulacion, de inicio
                              // a final, no se interrumpe
end

initial begin
  reset = 1;
  #50;
  reset = 0; D = 4'b0010;
  #50;
  D = 4'b1110;
  #50;
  D = 4'b1010;
  #50;
  reset = 1; D = 4'b1010;
  #20;
  reset = 0; D = 4'b1111;
  #20;
  D = 4'b0101;
end

initial begin
//para terminar la simulacion
  #300 $finish;
end

initial begin
$dumpfile("Dflop_tb.vcd");
$dumpvars(0,testbench);
end

endmodule

Laboratorio#6/Ejercicio5/Dflop_tb.vcd
$date
	Thu Sep 03 16:13:14 2020
$end
$version
	Icarus Verilog
$end
$timescale
	1ps
$end
$scope module testbench $end
$var wire 4 ! Y [3:0] $end
$var reg 4 " D [3:0] $end
$var reg 1 # clk $end
$var reg 1 $ reset $end
$scope module df1 $end
$var wire 4 % D [3:0] $end
$var wire 1 $ areset $end
$var wire 1 # clk $end
$var reg 4 & Y [3:0] $end
$upscope $end
$upscope $end
$enddefinitions $end
#0
$dumpvars
b0 &
bx %
1$
0#
bx "
b0 !
$end
#10
1#
#20
0#
#30
1#
#40
0#
#50
b10 !
b10 &
1#
b10 "
b10 %
0$
#60
0#
#70
1#
#80
0#
#90
1#
#100
0#
b1110 "
b1110 %
#110
b1110 !
b1110 &
1#
#120
0#
#130
1#
#140
0#
#150
b1010 !
b1010 &
1#
b1010 "
b1010 %
#160
0#
#170
1#
#180
0#
#190
1#
#200
b0 !
b0 &
0#
1$
#210
1#
#220
0#
b1111 "
b1111 %
0$
#230
b1111 !
b1111 &
1#
#240
0#
b101 "
b101 %
#250
b101 !
b101 &
1#
