Laboratorio#8/ALU/ALU.v
///////////////////////////////////////////////////////////////////////////////
//JOSE LUIS ALVAREZ PINEDA
//19392
//Laboratorio electronica digital
//ALU laboratorio #08
///////////////////////////////////////////////////////////////////////////////

module ALU #(parameter N = 4) //Parametro para el tamaño de los bits en las entradas
(
  input wire [2:0] sel,
  input wire[N-1:0] A,
  input wire[N-1:0] B,
  output reg[N-1:0] Y
  );


  always @ ( sel, A, B ) begin
  case (sel)
    3'b000: Y = A & B; // and logico
    3'b001: Y = A | B; // or logico
    3'b010: Y = A + B; // suma aritmetica
    3'b011: Y = 0; // no se usa por eleccion se coloca en 0
    3'b100: Y = A & ~B; // and logico con b negado
    3'b101: Y = A | ~B ; // or logico con b negado
    3'b110: Y = A - B; // resta aritmetica
    3'b111: Y = (A<B)? 'b1: 'b0; //si A es menor que B da 1, de lo contrario 0
    default: Y = 0; //si entra cualquier otro valor es 0 por eleccion
  endcase

  end
endmodule

Laboratorio#8/ALU/ALU_tb.v
module testbench();
reg[n-1:0] A;
reg[n-1:0] B;
reg[2:0] selector;
wire[n-1:0] Y;

parameter n = 4; //parametro para el modulo

ALU #(.N(n)) modALU (selector, A, B, Y); //instanciando el modulo de al ALU y
//sobreescribiendo el valor del parametro declarado

initial begin
//declarando los valores de A y B y haciendo que el selector aumente para probar los casos.
A = 1;
B = 4;
selector = 0;
forever #1 selector = selector + 1;
end

//terminar el ciclo luego de 10 unidades de tiempo
initial begin
  #10 $finish;
end

//datos de GTKWAVE
initial begin
$dumpfile("ALU_tb.vcd");
$dumpvars(0, testbench);
end

endmodule //

Laboratorio#8/ALU/ALU_tb.vcd
$date
	Thu Oct 22 16:50:33 2020
$end
$version
	Icarus Verilog
$end
$timescale
	1ps
$end
$scope module testbench $end
$var wire 4 ! Y [3:0] $end
$var reg 4 " A [3:0] $end
$var reg 4 # B [3:0] $end
$var reg 3 $ selector [2:0] $end
$scope module modALU $end
$var wire 4 % A [3:0] $end
$var wire 4 & B [3:0] $end
$var wire 3 ' sel [2:0] $end
$var reg 4 ( Y [3:0] $end
$upscope $end
$upscope $end
$enddefinitions $end
#0
$dumpvars
b0 (
b0 '
b100 &
b1 %
b0 $
b100 #
b1 "
b0 !
$end
#1
b101 !
b101 (
b1 $
b1 '
#2
b10 $
b10 '
#3
b0 !
b0 (
b11 $
b11 '
#4
b1 !
b1 (
b100 $
b100 '
#5
b1011 !
b1011 (
b101 $
b101 '
#6
b1101 !
b1101 (
b110 $
b110 '
#7
b1 !
b1 (
b111 $
b111 '
#8
b0 !
b0 (
b0 $
b0 '
#9
b101 !
b101 (
b1 $
b1 '
#10
b10 $
b10 '
