PROYECTO#1-FSM/ScriptsDelProyecto/FSMselector/FSMproy1.v
///////////////////////////////////////////////////////////////////////////////
///Jose Luis Alvarez Pineda
///19392
///Electronica digital
///Proyecto 1
///FSM del selector
///////////////////////////////////////////////////////////////////////////////

//implementacion de un FF con solo reset asincrono y es del tipo D
module Dflop(
  input wire areset, clk,
  input wire [3:0] D,
  output reg [3:0] Y);

    always @ ( posedge clk, posedge areset) begin
      if (areset) Y <= 4'b0000;
      else Y <= D;
    end

endmodule

////////////////////////////////////////////////////////////////////////////////
//IMPLEMENTACION DE LA FSM DE EL SELECTOR
module SFMSelector(
  input areset,clk,
  input wire C,T,L,A,N,V,
  output wire [3:0]S,
  output wire [3:0]Sf,
  output wire [3:0]SA);

 Dflop FF1 (areset, clk, Sf, S);

//SON LOS ESTADOS FUTUROS INTERNOS DE LA MAQUINA
//ECUACIONES se encuentran en la pagina 10 del documento escrito
 assign Sf[3] = (S[3] & ~S[2]) | (S[3] & ~S[1]) | (S[3] & ~S[0]) |(~S[2] & ~S[1] & ~S[0] & ~C & T);

 assign Sf[2] = (~S[3] & S[2]) | (S[2] & ~S[1]) | (S[2] & ~S[0]) | (~S[3] & S[1] & ~N & V)
                | (S[1] & ~S[0] & ~N & V) | (~S[3] & S[1] & N & ~V)
                | (S[1] & ~S[0] & N & ~V) | (S[3] & ~S[1] & S[0] & ~N & V);

 assign Sf[1] = (S[2] & S[1] & ~S[0]) | (~S[3] & ~S[2] & S[0] & ~L & A) |
                (~S[3] & ~S[2] & S[0] & L & ~A) | (S[3] & ~S[2] & S[0] & N & ~V) |
                (~S[3] & S[1] & S[0]) | (S[3] & ~S[2] & S[1] & V) | (~S[2] & S[1] & N & V) |
                (~S[2] & S[1] & ~N & ~V) | (S[3] & ~S[2] & ~S[1] & ~S[0] & ~L & A) ;

 assign Sf[0] = (~S[3] & S[2] & S[0]) | (S[2] & ~S[1] & S[0]) | (~S[3] & ~S[2] & S[1] & ~N & V) |
                (S[3] & ~S[2] & S[1] & N & ~V) | (S[3] & ~S[2] & ~S[1] & ~S[0] & L & ~A) |
                | (~S[3] & ~S[1] & S[0] & ~L) | (~S[3] & ~S[1] & S[0] & A) | (S[3] & ~S[2] & S[0] & N) |
                (~S[2] & S[1] & S[0] & ~N) | (~S[2] & S[1] & S[0] & V) | (S[3] & ~S[2] & S[0] & ~V) |
                (~S[3] & ~S[2] & ~S[1] & ~S[0] & C & ~T);
//ASIGNACION DE LAS SALIDAS DEL MODULO
//ECUACIONES se encuentran en la pagina 11 del documento escrito.
  assign SA[3] = S[2] | (S[3] & S[1] & S[0]);

  assign SA[2] = (~S[3] & S[2] & S[0]) | (S[3] & S[2] & ~S[0]);

  assign SA[1] = (S[2] & S[1]) | (S[3] & S[2] & S[0]) | (~S[3] & S[1] & S[0]) | (S[3] & S[1] & ~S[0]);

  assign SA[0] = S[3];

endmodule

PROYECTO#1-FSM/ScriptsDelProyecto/FSMselector/FSMproy1_tb.v
module BancoDePrueba();
reg Cafe, Te, Leche, Agua, Nada, Vainilla;
reg RESET, CLK, CLK2;
wire [3:0]Sactual;
wire [3:0]Sfuturo;
wire [3:0]SA;

SFMSelector fs1(RESET, CLK, Cafe, Te, Leche, Agua, Nada, Vainilla, Sactual, Sfuturo, SA);

//CLOCK 1, para las FSM
initial begin
  CLK = 0;
  forever #1 CLK = ~CLK; //cambio ininterrumpido del CLOCK durante todo el tiempo.
end

///////////////////////////////////////////////////////////////////////////////
/// El numero de prueba de timming previo a la asignacion de las variables
/// coincide con la del documento escrito del proyecto.
/// ESTOS SON DE LA SECCION DE LA MAQUINA SELECTORA paginas 16 a la 21
///////////////////////////////////////////////////////////////////////////////
initial begin
//primera prueba, timming 1
RESET = 1; Cafe = 0; Te= 0; Leche= 0; Agua = 0; Nada = 0; Vainilla = 0;
#1 RESET = 0; Cafe = 1; Te = 1; Leche =1; Agua =1; Nada =1; Vainilla =1;
#2 Cafe = 0; Te = 0; Leche =0; Agua = 0; Nada =0; Vainilla =0;
#3 Cafe = 1; Te = 1;
#2 Te= 0;
#2 Cafe= 0; Leche= 1; Agua = 1;
#2 Leche = 0; Agua = 0;
#2 Leche = 1;
#2 Nada = 1; Vainilla = 1;
#2 Nada = 0; Vainilla = 0;
#2 Nada = 1;
#2 Nada = 0;

//segunda prueba, timming 2
#10 RESET = 1; Leche = 0;
#2 RESET = 0;
#2 Cafe = 1;
#4 RESET = 1;
#1 Cafe = 0;
#1 RESET = 0;
#2 Te = 1;
#4 RESET = 1;
#1 Te = 0;
#1 RESET = 0;

//tercera prueba, timming 3
#10 Cafe = 1;
#4 Cafe = 0; Leche = 1;
#4 RESET = 1; Leche = 0;
#2 Cafe = 1; RESET = 0;
#4 Cafe = 0; Agua = 1;
#2 RESET = 1; Agua = 0;
#2 RESET = 0;

//cuarta prueba, timming 4
#10 Te= 1;
#4 Te = 0; Leche = 1;
#4 RESET = 1; Leche = 0;
#2 Te = 1; RESET = 0;
#4 Te= 0; Agua = 1;
#2 RESET = 1; Agua = 0;
#2 RESET = 0;

//quinta prueba, timming 5
#10 Cafe = 1;
#4 Cafe = 0; Leche = 1;
#2 Leche = 0; Nada = 1;
#4 RESET = 1; Nada = 0;
#2 RESET = 0;
#8 Cafe = 1;
#4 Cafe = 0; Leche = 1;
#2 Leche = 0; Vainilla = 1;
#4 RESET = 1; Vainilla = 0;
#2 RESET = 0;

#10 Cafe = 1;
#4 Cafe = 0; Agua = 1;
#2 Agua = 0; Nada = 1;
#4 RESET = 1; Nada = 0;
#2 RESET = 0;
#8 Cafe = 1;
#4 Cafe = 0; Agua = 1;
#2 Agua = 0; Vainilla = 1;
#4 RESET = 1; Vainilla = 0;
#2 RESET = 0;

//sexta prueba, timming 6
#10 Te = 1;
#4 Te = 0; Leche = 1;
#2 Leche = 0; Nada = 1;
#4 RESET = 1; Nada = 0;
#2 RESET = 0;
#8 Te = 1;
#4 Te = 0; Leche = 1;
#2 Leche = 0; Vainilla = 1;
#4 RESET = 1; Vainilla = 0;
#2 RESET = 0;

#10 Te = 1;
#4 Te = 0; Agua = 1;
#2 Agua = 0; Nada = 1;
#4 RESET = 1; Nada = 0;
#2 RESET = 0;
#8 Te = 1;
#4 Te = 0; Agua = 1;
#2 Agua = 0; Vainilla = 1;
#4 RESET = 1; Vainilla = 0;
#2 RESET = 0;

//Septima prueba, timing 7
#6 Cafe = 1; Leche = 1; Nada = 1;
#8 RESET = 1; Nada = 0;
#2 RESET =0; Vainilla = 1;
#8 RESET =1; Vainilla = 0;
#2 RESET = 0; Cafe = 0; Leche = 0;

//Octava prueba, timing 8
#6 Cafe = 1; Agua = 1; Nada = 1;
#8 RESET = 1; Nada = 0;
#2 RESET =0; Vainilla = 1;
#8 RESET =1; Vainilla = 0;
#2 RESET = 0; Cafe = 0; Agua = 0;

//Septima prueba, timing 9
#6 Te = 1; Leche = 1; Nada = 1;
#8 RESET = 1; Nada = 0;
#2 RESET =0; Vainilla = 1;
#8 RESET =1; Vainilla = 0;
#2 RESET = 0; Te = 0; Leche = 0;

//Octava prueba, timing 10
#6 Te = 1; Agua = 1; Nada = 1;
#8 RESET = 1; Nada = 0;
#2 RESET =0; Vainilla = 1;
#8 RESET =1; Vainilla = 0;
#2 RESET = 0; Te = 0; Agua = 0;

end
///////////////////////////////////////////////////////////////////////////////
initial begin
  #400 $finish;
end

initial begin
$dumpfile ("FSMproy1_tb.vcd");
$dumpvars (0, BancoDePrueba);

end

endmodule

PROYECTO#1-FSM/ScriptsDelProyecto/FSMselector/FSMproy1_tb.vcd
$date
	Sun Oct 04 17:22:13 2020
$end
$version
	Icarus Verilog
$end
$timescale
	1ps
$end
$scope module BancoDePrueba $end
$var wire 4 ! Sfuturo [3:0] $end
$var wire 4 " Sactual [3:0] $end
$var wire 4 # SA [3:0] $end
$var reg 1 $ Agua $end
$var reg 1 % CLK $end
$var reg 1 & Cafe $end
$var reg 1 ' Leche $end
$var reg 1 ( Nada $end
$var reg 1 ) RESET $end
$var reg 1 * Te $end
$var reg 1 + Vainilla $end
$scope module fs1 $end
$var wire 1 $ A $end
$var wire 1 & C $end
$var wire 1 ' L $end
$var wire 1 ( N $end
$var wire 1 * T $end
$var wire 1 + V $end
$var wire 1 ) areset $end
$var wire 1 % clk $end
$var wire 4 , Sf [3:0] $end
$var wire 4 - SA [3:0] $end
$var wire 4 . S [3:0] $end
$scope module FF1 $end
$var wire 4 / D [3:0] $end
$var wire 1 ) areset $end
$var wire 1 % clk $end
$var reg 4 0 Y [3:0] $end
$upscope $end
$upscope $end
$upscope $end
$enddefinitions $end
#0
$dumpvars
b0 0
b0 /
b0 .
b0 -
b0 ,
0+
0*
1)
0(
0'
0&
0%
0$
b0 #
b0 "
b0 !
$end
#1
b0 !
b0 ,
b0 /
1+
1(
1$
1'
1*
1&
0)
1%
#2
0%
#3
1%
0+
0(
0$
0'
0*
0&
#4
0%
#5
1%
#6
b0 !
b0 ,
b0 /
0%
1*
1&
#7
1%
#8
b1 !
b1 ,
b1 /
0%
0*
#9
b1 !
b1 ,
b1 /
b1 "
b1 .
b1 0
1%
#10
b1 !
b1 ,
b1 /
0%
1$
1'
0&
#11
1%
#12
b1 !
b1 ,
b1 /
0%
0$
0'
#13
1%
#14
b10 !
b10 ,
b10 /
0%
1'
#15
b10 "
b10 .
b10 0
1%
#16
b10 !
b10 ,
b10 /
0%
1+
1(
#17
1%
#18
0%
0+
0(
#19
1%
#20
b100 !
b100 ,
b100 /
0%
1(
#21
b1000 #
b1000 -
b100 "
b100 .
b100 0
1%
#22
0%
0(
#23
1%
#24
0%
#25
1%
#26
0%
#27
1%
#28
0%
#29
1%
#30
0%
#31
1%
#32
b0 !
b0 ,
b0 /
b0 #
b0 -
b0 "
b0 .
b0 0
0%
0'
1)
#33
1%
#34
0%
0)
#35
1%
#36
b1 !
b1 ,
b1 /
0%
1&
#37
b1 !
b1 ,
b1 /
b1 "
b1 .
b1 0
1%
#38
0%
#39
1%
#40
b0 "
b0 .
b0 0
0%
1)
#41
b0 !
b0 ,
b0 /
1%
0&
#42
0%
0)
#43
1%
#44
b1000 !
b1000 ,
b1000 /
0%
1*
#45
b1 #
b1 -
b1000 "
b1000 .
b1000 0
1%
#46
0%
#47
1%
#48
b0 #
b0 -
b0 "
b0 .
b0 0
0%
1)
#49
b0 !
b0 ,
b0 /
1%
0*
#50
0%
0)
#51
1%
#52
0%
#53
1%
#54
0%
#55
1%
#56
0%
#57
1%
#58
0%
#59
1%
#60
b1 !
b1 ,
b1 /
0%
1&
#61
b1 !
b1 ,
b1 /
b1 "
b1 .
b1 0
1%
#62
0%
#63
1%
#64
b10 !
b10 ,
b10 /
0%
1'
0&
#65
b10 "
b10 .
b10 0
1%
#66
0%
#67
1%
#68
b0 !
b0 ,
b0 /
b0 "
b0 .
b0 0
0%
0'
1)
#69
1%
#70
b1 !
b1 ,
b1 /
0%
0)
1&
#71
b1 !
b1 ,
b1 /
b1 "
b1 .
b1 0
1%
#72
0%
#73
1%
#74
b11 !
b11 ,
b11 /
0%
1$
0&
#75
b10 #
b10 -
b11 "
b11 .
b11 0
1%
#76
b0 !
b0 ,
b0 /
b0 #
b0 -
b0 "
b0 .
b0 0
0%
0$
1)
#77
1%
#78
0%
0)
#79
1%
#80
0%
#81
1%
#82
0%
#83
1%
#84
0%
#85
1%
#86
0%
#87
1%
#88
b1000 !
b1000 ,
b1000 /
0%
1*
#89
b1 #
b1 -
b1000 "
b1000 .
b1000 0
1%
#90
0%
#91
1%
#92
b1001 !
b1001 ,
b1001 /
0%
1'
0*
#93
b1001 "
b1001 .
b1001 0
1%
#94
0%
#95
1%
#96
b0 !
b0 ,
b0 /
b0 #
b0 -
b0 "
b0 .
b0 0
0%
0'
1)
#97
1%
#98
b1000 !
b1000 ,
b1000 /
0%
0)
1*
#99
b1 #
b1 -
b1000 "
b1000 .
b1000 0
1%
#100
0%
#101
1%
#102
b1010 !
b1010 ,
b1010 /
0%
1$
0*
#103
b11 #
b11 -
b1010 "
b1010 .
b1010 0
1%
#104
b0 !
b0 ,
b0 /
b0 #
b0 -
b0 "
b0 .
b0 0
0%
0$
1)
#105
1%
#106
0%
0)
#107
1%
#108
0%
#109
1%
#110
0%
#111
1%
#112
0%
#113
1%
#114
0%
#115
1%
#116
b1 !
b1 ,
b1 /
0%
1&
#117
b1 !
b1 ,
b1 /
b1 "
b1 .
b1 0
1%
#118
0%
#119
1%
#120
b10 !
b10 ,
b10 /
0%
1'
0&
#121
b10 "
b10 .
b10 0
1%
#122
b100 !
b100 ,
b100 /
0%
1(
0'
#123
b1000 #
b1000 -
b100 "
b100 .
b100 0
1%
#124
0%
#125
1%
#126
b0 !
b0 ,
b0 /
b0 #
b0 -
b0 "
b0 .
b0 0
0%
0(
1)
#127
1%
#128
0%
0)
#129
1%
#130
0%
#131
1%
#132
0%
#133
1%
#134
0%
#135
1%
#136
b1 !
b1 ,
b1 /
0%
1&
#137
b1 !
b1 ,
b1 /
b1 "
b1 .
b1 0
1%
#138
0%
#139
1%
#140
b10 !
b10 ,
b10 /
0%
1'
0&
#141
b10 "
b10 .
b10 0
1%
#142
b101 !
b101 ,
b101 /
0%
1+
0'
#143
b1100 #
b1100 -
b101 "
b101 .
b101 0
1%
#144
0%
#145
1%
#146
b0 !
b0 ,
b0 /
b0 #
b0 -
b0 "
b0 .
b0 0
0%
0+
1)
#147
1%
#148
0%
0)
#149
1%
#150
0%
#151
1%
#152
0%
#153
1%
#154
0%
#155
1%
#156
0%
#157
1%
#158
b1 !
b1 ,
b1 /
0%
1&
#159
b1 !
b1 ,
b1 /
b1 "
b1 .
b1 0
1%
#160
0%
#161
1%
#162
b11 !
b11 ,
b11 /
0%
1$
0&
#163
b10 #
b10 -
b11 "
b11 .
b11 0
1%
#164
b110 !
b110 ,
b110 /
0%
1(
0$
#165
b110 !
b110 ,
b110 /
b1010 #
b1010 -
b110 "
b110 .
b110 0
1%
#166
0%
#167
1%
#168
b0 !
b0 ,
b0 /
b0 #
b0 -
b0 "
b0 .
b0 0
0%
0(
1)
#169
1%
#170
0%
0)
#171
1%
#172
0%
#173
1%
#174
0%
#175
1%
#176
0%
#177
1%
#178
b1 !
b1 ,
b1 /
0%
1&
#179
b1 !
b1 ,
b1 /
b1 "
b1 .
b1 0
1%
#180
0%
#181
1%
#182
b11 !
b11 ,
b11 /
0%
1$
0&
#183
b10 #
b10 -
b11 "
b11 .
b11 0
1%
#184
b111 !
b111 ,
b111 /
0%
1+
0$
#185
b1110 #
b1110 -
b111 "
b111 .
b111 0
1%
#186
0%
#187
1%
#188
b0 !
b0 ,
b0 /
b0 #
b0 -
b0 "
b0 .
b0 0
0%
0+
1)
#189
1%
#190
0%
0)
#191
1%
#192
0%
#193
1%
#194
0%
#195
1%
#196
0%
#197
1%
#198
0%
#199
1%
#200
b1000 !
b1000 ,
b1000 /
0%
1*
#201
b1 #
b1 -
b1000 "
b1000 .
b1000 0
1%
#202
0%
#203
1%
#204
b1001 !
b1001 ,
b1001 /
0%
1'
0*
#205
b1001 "
b1001 .
b1001 0
1%
#206
b1011 !
b1011 ,
b1011 /
0%
1(
0'
#207
b1001 #
b1001 -
b1011 "
b1011 .
b1011 0
1%
#208
0%
#209
1%
#210
b0 !
b0 ,
b0 /
b0 #
b0 -
b0 "
b0 .
b0 0
0%
0(
1)
#211
1%
#212
0%
0)
#213
1%
#214
0%
#215
1%
#216
0%
#217
1%
#218
0%
#219
1%
#220
b1000 !
b1000 ,
b1000 /
0%
1*
#221
b1 #
b1 -
b1000 "
b1000 .
b1000 0
1%
#222
0%
#223
1%
#224
b1001 !
b1001 ,
b1001 /
0%
1'
0*
#225
b1001 "
b1001 .
b1001 0
1%
#226
b1100 !
b1100 ,
b1100 /
0%
1+
0'
#227
b1100 !
b1100 ,
b1100 /
b1101 #
b1101 -
b1100 "
b1100 .
b1100 0
1%
#228
0%
#229
1%
#230
b0 !
b0 ,
b0 /
b0 #
b0 -
b0 "
b0 .
b0 0
0%
0+
1)
#231
1%
#232
0%
0)
#233
1%
#234
0%
#235
1%
#236
0%
#237
1%
#238
0%
#239
1%
#240
0%
#241
1%
#242
b1000 !
b1000 ,
b1000 /
0%
1*
#243
b1 #
b1 -
b1000 "
b1000 .
b1000 0
1%
#244
0%
#245
1%
#246
b1010 !
b1010 ,
b1010 /
0%
1$
0*
#247
b11 #
b11 -
b1010 "
b1010 .
b1010 0
1%
#248
b1101 !
b1101 ,
b1101 /
0%
1(
0$
#249
b1101 !
b1101 ,
b1101 /
b1011 #
b1011 -
b1101 "
b1101 .
b1101 0
1%
#250
0%
#251
1%
#252
b0 !
b0 ,
b0 /
b0 #
b0 -
b0 "
b0 .
b0 0
0%
0(
1)
#253
1%
#254
0%
0)
#255
1%
#256
0%
#257
1%
#258
0%
#259
1%
#260
0%
#261
1%
#262
b1000 !
b1000 ,
b1000 /
0%
1*
#263
b1 #
b1 -
b1000 "
b1000 .
b1000 0
1%
#264
0%
#265
1%
#266
b1010 !
b1010 ,
b1010 /
0%
1$
0*
#267
b11 #
b11 -
b1010 "
b1010 .
b1010 0
1%
#268
b1110 !
b1110 ,
b1110 /
0%
1+
0$
#269
b1110 !
b1110 ,
b1110 /
b1111 #
b1111 -
b1110 "
b1110 .
b1110 0
1%
#270
0%
#271
1%
#272
b0 !
b0 ,
b0 /
b0 #
b0 -
b0 "
b0 .
b0 0
0%
0+
1)
#273
1%
#274
0%
0)
#275
1%
#276
0%
#277
1%
#278
0%
#279
1%
#280
b1 !
b1 ,
b1 /
0%
1(
1'
1&
#281
b10 !
b10 ,
b10 /
b1 "
b1 .
b1 0
1%
#282
0%
#283
b100 !
b100 ,
b100 /
b10 "
b10 .
b10 0
1%
#284
0%
#285
b1000 #
b1000 -
b100 "
b100 .
b100 0
1%
#286
0%
#287
1%
#288
b1 !
b1 ,
b1 /
b0 #
b0 -
b0 "
b0 .
b0 0
0%
0(
1)
#289
1%
#290
0%
1+
0)
#291
b10 !
b10 ,
b10 /
b1 "
b1 .
b1 0
1%
#292
0%
#293
b101 !
b101 ,
b101 /
b10 "
b10 .
b10 0
1%
#294
0%
#295
b101 !
b101 ,
b101 /
b1100 #
b1100 -
b101 "
b101 .
b101 0
1%
#296
0%
#297
1%
#298
b1 !
b1 ,
b1 /
b0 #
b0 -
b0 "
b0 .
b0 0
0%
0+
1)
#299
1%
#300
b0 !
b0 ,
b0 /
0%
0'
0&
0)
#301
1%
#302
0%
#303
1%
#304
0%
#305
1%
#306
b1 !
b1 ,
b1 /
0%
1(
1$
1&
#307
b11 !
b11 ,
b11 /
b1 "
b1 .
b1 0
1%
#308
0%
#309
b110 !
b110 ,
b110 /
b10 #
b10 -
b11 "
b11 .
b11 0
1%
#310
0%
#311
b1010 #
b1010 -
b110 "
b110 .
b110 0
1%
#312
0%
#313
1%
#314
b1 !
b1 ,
b1 /
b0 #
b0 -
b0 "
b0 .
b0 0
0%
0(
1)
#315
1%
#316
0%
1+
0)
#317
b11 !
b11 ,
b11 /
b1 "
b1 .
b1 0
1%
#318
0%
#319
b111 !
b111 ,
b111 /
b10 #
b10 -
b11 "
b11 .
b11 0
1%
#320
0%
#321
b1110 #
b1110 -
b111 "
b111 .
b111 0
1%
#322
0%
#323
1%
#324
b1 !
b1 ,
b1 /
b0 #
b0 -
b0 "
b0 .
b0 0
0%
0+
1)
#325
1%
#326
b0 !
b0 ,
b0 /
0%
0$
0&
0)
#327
1%
#328
0%
#329
1%
#330
0%
#331
1%
#332
b1000 !
b1000 ,
b1000 /
0%
1(
1'
1*
#333
b1001 !
b1001 ,
b1001 /
b1 #
b1 -
b1000 "
b1000 .
b1000 0
1%
#334
0%
#335
b1011 !
b1011 ,
b1011 /
b1001 "
b1001 .
b1001 0
1%
#336
0%
#337
b1001 #
b1001 -
b1011 "
b1011 .
b1011 0
1%
#338
0%
#339
1%
#340
b1000 !
b1000 ,
b1000 /
b0 #
b0 -
b0 "
b0 .
b0 0
0%
0(
1)
#341
1%
#342
0%
1+
0)
#343
b1001 !
b1001 ,
b1001 /
b1 #
b1 -
b1000 "
b1000 .
b1000 0
1%
#344
0%
#345
b1100 !
b1100 ,
b1100 /
b1001 "
b1001 .
b1001 0
1%
#346
0%
#347
b1100 !
b1100 ,
b1100 /
b1101 #
b1101 -
b1100 "
b1100 .
b1100 0
1%
#348
0%
#349
1%
#350
b1000 !
b1000 ,
b1000 /
b0 #
b0 -
b0 "
b0 .
b0 0
0%
0+
1)
#351
1%
#352
b0 !
b0 ,
b0 /
0%
0'
0*
0)
#353
1%
#354
0%
#355
1%
#356
0%
#357
1%
#358
b1000 !
b1000 ,
b1000 /
0%
1(
1$
1*
#359
b1010 !
b1010 ,
b1010 /
b1 #
b1 -
b1000 "
b1000 .
b1000 0
1%
#360
0%
#361
b1101 !
b1101 ,
b1101 /
b11 #
b11 -
b1010 "
b1010 .
b1010 0
1%
#362
0%
#363
b1101 !
b1101 ,
b1101 /
b1011 #
b1011 -
b1101 "
b1101 .
b1101 0
1%
#364
0%
#365
1%
#366
b1000 !
b1000 ,
b1000 /
b0 #
b0 -
b0 "
b0 .
b0 0
0%
0(
1)
#367
1%
#368
0%
1+
0)
#369
b1010 !
b1010 ,
b1010 /
b1 #
b1 -
b1000 "
b1000 .
b1000 0
1%
#370
0%
#371
b1110 !
b1110 ,
b1110 /
b11 #
b11 -
b1010 "
b1010 .
b1010 0
1%
#372
0%
#373
b1110 !
b1110 ,
b1110 /
b1111 #
b1111 -
b1110 "
b1110 .
b1110 0
1%
#374
0%
#375
1%
#376
b1000 !
b1000 ,
b1000 /
b0 #
b0 -
b0 "
b0 .
b0 0
0%
0+
1)
#377
1%
#378
b0 !
b0 ,
b0 /
0%
0$
0*
0)
