Laboratorio#3/Ejercicio_04_POS/LAB04_POS.v
module LAB04_POS();

// POS de la tabla04 del laboratorio 3

  reg A, B, C, D;
  wire NA, NB, NC, ND, w1, w2, w3, w4, w5, w6, w7, w8, w9, out;


  not s1(NA,A); //(salida, entradas)
  not s2(NB,B);
  not s3(NC,C);
  not s4(ND,D);
  or sum1(w1,A,B,C,ND);
  or sum2(w2,A,NB,C,D);
  or sum3(w3,A,NB,C,ND);
  or sum4(w4,NA,B,C,ND);
  or sum5(w5,NA,B,NC,ND);
  or sum6(w6,NA,NB,C,D);
  or sum7(w7,NA,NB,C,ND);
  or sum8(w8,NA,NB,NC,D);
  or sum9(w9,NA,NB,NC,ND);
  and mult1(out,w1,w2,w3,w4,w5,w6,w7,w8,w9);

  initial begin
    $display("A B C D| Y");
    $display("----------");

    $monitor("%b %b %b %b| %b", A, B, C, D, out);
    A = 0; B = 0; C=0; D=0;
    #1 A = 0; B = 0; C = 0; D = 0;
    #1 A = 0; B = 0; C = 0; D = 1;
    #1 A = 0; B = 0; C = 1; D = 0;
    #1 A = 0; B = 0; C = 1; D = 1;
    #1 A = 0; B = 1; C = 0; D = 0;
    #1 A = 0; B = 1; C = 0; D = 1;
    #1 A = 0; B = 1; C = 1; D = 0;
    #1 A = 0; B = 1; C = 1; D = 1;
    #1 A = 1; B = 0; C = 0; D = 0;
    #1 A = 1; B = 0; C = 0; D = 1;
    #1 A = 1; B = 0; C = 1; D = 0;
    #1 A = 1; B = 0; C = 1; D = 1;
    #1 A = 1; B = 1; C = 0; D = 0;
    #1 A = 1; B = 1; C = 0; D = 1;
    #1 A = 1; B = 1; C = 1; D = 0;
    #1 A = 1; B = 1; C = 1; D = 1;
    #1 $finish;
  end

  initial
    begin
      $dumpfile("LAB04_POS_tb.vcd");
      $dumpvars(0, LAB04_POS);
    end

endmodule

Laboratorio#3/Ejercicio_04_POS/LAB04_POS_tb.vcd
$date
	Thu Jul 30 15:49:44 2020
$end
$version
	Icarus Verilog
$end
$timescale
	1ps
$end
$scope module LAB04_POS $end
$var wire 1 ! NA $end
$var wire 1 " NB $end
$var wire 1 # NC $end
$var wire 1 $ ND $end
$var wire 1 % out $end
$var wire 1 & w1 $end
$var wire 1 ' w2 $end
$var wire 1 ( w3 $end
$var wire 1 ) w4 $end
$var wire 1 * w5 $end
$var wire 1 + w6 $end
$var wire 1 , w7 $end
$var wire 1 - w8 $end
$var wire 1 . w9 $end
$var reg 1 / A $end
$var reg 1 0 B $end
$var reg 1 1 C $end
$var reg 1 2 D $end
$upscope $end
$enddefinitions $end
#0
$dumpvars
02
01
00
0/
1.
1-
1,
1+
1*
1)
1(
1'
1&
1%
1$
1#
1"
1!
$end
#2
0%
0&
0$
12
#3
1%
1$
1&
0#
02
11
#4
0$
12
#5
0%
1$
1(
0'
1#
0"
02
01
10
#6
0(
1'
0$
12
#7
1%
1$
1(
0#
02
11
#8
0$
12
#9
1%
1$
1#
1*
1)
1"
0!
02
01
00
1/
#10
0%
0)
0$
12
#11
1%
1$
1)
0#
02
11
#12
0%
0*
0$
12
#13
1$
1,
0+
1#
1*
0"
02
01
10
#14
0,
1+
0$
12
#15
0-
1$
1,
0#
02
11
#16
0.
1-
0$
12
