Laboratorio#6/Ejercicio3/contador.v
///////////////////////////////////////////////////////////////////////////////
///Jose Luis Alvarez Pineda
///19392
///Electronica digital
///Laboratorio #06, ejercicio #3 implementado en verilog
///////////////////////////////////////////////////////////////////////////////
//se reutilizo el flip flop del ejercicio 5
module Dflop(input logic clk,
  input logic areset,
  input logic[2:0] D,
  output reg[2:0] Y);
//areset es el reset asincrono en el flip flop, no es necesario el clock para cambiar el
//estado
  always @ (posedge clk, posedge areset) begin
      //if para evitar que otro valor pase cuando se active el reset
      if(areset)
      Y <= 3'b000;
      else
      Y <= D;
  end

endmodule

////////////////////////////////////////////////////////////////////////////////
module EJ3(input logic clk,
  input logic reset,
  input logic A,
  output wire[2:0] sal);

  wire[2:0] S;

  Dflop FD1 (clk, reset, S, sal);
  
  assign S[2] = (sal[2] & sal[0]) | (sal[1] & ~ sal[0] & A) | (~sal[1] & ~sal[0] & ~A);
  assign S[1] = (sal[1] & ~sal[0]) | (~sal[2] & sal[0] & A) | (sal[2] & sal[0] & ~A);
  assign S[0] = (sal[2] & sal[1] & A) | (~sal[2] & ~sal[1] & A) | (~sal[2] & sal[1] & ~A)
                  | (sal[2] & ~sal[1] & ~A);

endmodule

Laboratorio#6/Ejercicio3/contador_tb.v
module testbench();
//variables a utilizar para el contador gray
reg[2:0] D; // ya que no se utilizan valores de asignacion continua
reg clk;    // se asignan como registros
reg reset;
reg A;
wire[2:0] Y; // cable que si acepta asignacion continua (mantiene el valor de la salida del FF)

EJ3 cont1(clk, reset, A, Y);// objeto de contador

initial begin
//bloque para generar el reloj, inicia en 0 y cada 10 unidades de tiempo
//cambia su estado.
  clk = 0;
      forever #10 clk = ~clk; //corre durante toda la simulacion, de inicio
                              // a final, no se interrumpe
end

initial begin
  reset = 1;
  A = 1;
  #5;
  reset = 0;
  #50 A = 0;
  #50 A = 1;
  #100 A = 0;
  #200 A = 1;
end

initial begin
//para terminar la simulacion
  #500 $finish;
end

initial begin
$dumpfile("contador_tb.vcd");
$dumpvars(0,testbench);
end

endmodule

Laboratorio#6/Ejercicio3/contador_tb.vcd
$date
	Thu Sep 03 17:06:58 2020
$end
$version
	Icarus Verilog
$end
$timescale
	1ps
$end
$scope module testbench $end
$var wire 3 ! Y [2:0] $end
$var reg 1 " A $end
$var reg 1 # clk $end
$var reg 1 $ reset $end
$scope module cont1 $end
$var wire 1 " A $end
$var wire 1 # clk $end
$var wire 1 $ reset $end
$var wire 3 % sal [2:0] $end
$var wire 3 & S [2:0] $end
$scope module FD1 $end
$var wire 3 ' D [2:0] $end
$var wire 1 $ areset $end
$var wire 1 # clk $end
$var reg 3 ( Y [2:0] $end
$upscope $end
$upscope $end
$upscope $end
$enddefinitions $end
#0
$dumpvars
b0 (
b1 '
b1 &
b0 %
1$
0#
1"
b0 !
$end
#5
0$
#10
b11 &
b11 '
b1 !
b1 %
b1 (
1#
#20
0#
#30
b10 &
b10 '
b11 !
b11 %
b11 (
1#
#40
0#
#50
b110 &
b110 '
b10 !
b10 %
b10 (
1#
#55
b11 &
b11 '
0"
#60
0#
#70
b1 &
b1 '
b11 !
b11 %
b11 (
1#
#80
0#
#90
b0 &
b0 '
b1 !
b1 %
b1 (
1#
#100
0#
#105
b11 &
b11 '
1"
#110
b10 &
b10 '
b11 !
b11 %
b11 (
1#
#120
0#
#130
b110 &
b110 '
b10 !
b10 %
b10 (
1#
#140
0#
#150
b111 &
b111 '
b110 !
b110 %
b110 (
1#
#160
0#
#170
b101 &
b101 '
b111 !
b111 %
b111 (
1#
#180
0#
#190
b100 &
b100 '
b101 !
b101 %
b101 (
1#
#200
0#
#205
b111 &
b111 '
0"
#210
b110 &
b110 '
b111 !
b111 %
b111 (
1#
#220
0#
#230
b10 &
b10 '
b110 !
b110 %
b110 (
1#
#240
0#
#250
b11 &
b11 '
b10 !
b10 %
b10 (
1#
#260
0#
#270
b1 &
b1 '
b11 !
b11 %
b11 (
1#
#280
0#
#290
b0 &
b0 '
b1 !
b1 %
b1 (
1#
#300
0#
#310
b100 &
b100 '
b0 !
b0 %
b0 (
1#
#320
0#
#330
b101 &
b101 '
b100 !
b100 %
b100 (
1#
#340
0#
#350
b111 &
b111 '
b101 !
b101 %
b101 (
1#
#360
0#
#370
b110 &
b110 '
b111 !
b111 %
b111 (
1#
#380
0#
#390
b10 &
b10 '
b110 !
b110 %
b110 (
1#
#400
0#
#405
b111 &
b111 '
1"
#410
b101 &
b101 '
b111 !
b111 %
b111 (
1#
#420
0#
#430
b100 &
b100 '
b101 !
b101 %
b101 (
1#
#440
0#
#450
b0 &
b0 '
b100 !
b100 %
b100 (
1#
#460
0#
#470
b1 &
b1 '
b0 !
b0 %
b0 (
1#
#480
0#
#490
b11 &
b11 '
b1 !
b1 %
b1 (
1#
