Laboratorio#10/Ejercicio2/Ej2.v
//JOse Luis ALvarez Pineda
//19392
//seccion 21
//Laboratorio #10 ejercicio #2

//modulo del
module BusDriver(
  input wire enable,
  input wire [3:0] D,
  output wire [3:0] Y);

  assign Y = enable? D:'bz;

endmodule

//modulo de la ACCU
module ACCU(
  input wire clk,reset,enable,
  input wire[3:0] D,
  output reg[3:0] Y);

  always @ (posedge clk, posedge reset) begin
    if (reset == 1) Y <= 0;
    else if(enable == 1) Y <= D;
    else Y <= Y;
  end

endmodule

//modulo de la ALU
module ALU(
  input wire[3:0] A, B,
  input wire[2:0] selector,
  output wire [3:0] Y,
  output reg C, ZERO);

  //variable para manejar el carry
  reg[3:0] RESalu;//para darle el dato a la salida
  reg[4:0] carry;//para manejar el carry de las operaciones

  assign Y = RESalu;

      always @ ( selector, A, B) begin

      case (selector)
        3'b100: RESalu = ~(A & B); // and logico
        3'b011: begin RESalu = A + B; carry = {1'b0,A} + {1'b0,B}; end//suma de A y B
        3'b000: RESalu = A; //pasa el valor de A
        3'b010: RESalu =  B; //pasa el valor de B
        3'b001: begin RESalu = A - B; carry = {1'b0,A} - {1'b0,B}; end//resta de A y B
        default: begin RESalu = 0; carry = 0; end //si entra cualquier otro valor es 0 por eleccion
      endcase

      if (RESalu == 0) begin
        ZERO = 1;
      end
      else begin
        ZERO = 0;
      end

      if (carry[4] == 1) begin
        C = 1;
      end
      else begin
        C = 0;
      end

      end

endmodule

module Interconexion(
  input wire ENBusIn,ENBusOut,ENAccu,clk,reset,
  input wire [2:0] selectorALU,
  input wire [3:0] INBUS,
  output wire [1:0] CZ,
  output wire [3:0] Acum,
  output wire [3:0] SALBUSOut);

  wire[3:0] data_bus,ALUOUT;
//bus de entrada
BusDriver BUSIN(.enable(ENBusIn),.D(INBUS),.Y(data_bus));
//bus de salida
BusDriver BUSOUT(.enable(ENBusOut),.D(ALUOUT),.Y(SALBUSOut));
//accumulador
ACCU acumulador(.clk(clk),.reset(reset),.enable(ENAccu),.D(ALUOUT),.Y(Acum));
//ALU
ALU operaciones(.selector(selectorALU),.A(Acum),.B(data_bus),.Y(ALUOUT),.ZERO(CZ[0]),.C(CZ[1]));

endmodule

Laboratorio#10/Ejercicio2/Ej2_tb.v
module testbench();
reg CLK,reset,Enbusin,Enbusout,Enaccu;
reg [2:0] selAlu;
reg [3:0] dataIn;
wire [1:0]CarryZero;
wire [3:0]BusdeSalida;
wire [3:0]ACCUactual;

Interconexion ej2(.Acum(ACCUactual),.SALBUSOut(BusdeSalida),.CZ(CarryZero),.INBUS(dataIn),.selectorALU(selAlu),.ENAccu(Enaccu),.ENBusIn(Enbusin),.ENBusOut(Enbusout),.clk(CLK),.reset(reset));

initial begin
  CLK= 0;
  forever #1 CLK = ~CLK;
end


initial begin
reset = 1; Enbusin = 0; Enbusout = 0; Enaccu = 0; selAlu = 3'b000; dataIn = 4'b0011;
#1 reset = 0;
#1 Enaccu = 1; selAlu = 3'b010; //prueba dejar pasar B
#2 Enbusin = 1;
#2 Enbusout = 1; Enaccu = 0; dataIn = 4'b1010;
#1 selAlu = 3'b100; //prueba NAND
#2 selAlu = 3'b011; //prueba suma
#2 selAlu = 3'b000; //prueba pasa el valor de A
#2 selAlu = 3'b001; //resta de los valores
#9 dataIn = 4'b1100; selAlu = 3'b010; Enaccu = 1;//Pasa un nuevo valor a A
#2 Enaccu = 0;
#2 selAlu = 3'b001;//resta de los valores
#2 dataIn = 4'b0011; Enaccu = 1;//cambio de valor, nueva resta
#2 Enaccu = 0;//Nuevo valor en el accu, se hace una resta distinta
end

initial begin
  #100 $finish;
end

initial begin
$dumpfile("Ej2_tb.vcd");
$dumpvars(0, testbench);
end

endmodule

Laboratorio#10/Ejercicio2/Ej2_tb.vcd
$date
	Thu Nov 05 16:09:25 2020
$end
$version
	Icarus Verilog
$end
$timescale
	1ps
$end
$scope module testbench $end
$var wire 2 ! CarryZero [1:0] $end
$var wire 4 " BusdeSalida [3:0] $end
$var wire 4 # ACCUactual [3:0] $end
$var reg 1 $ CLK $end
$var reg 1 % Enaccu $end
$var reg 1 & Enbusin $end
$var reg 1 ' Enbusout $end
$var reg 4 ( dataIn [3:0] $end
$var reg 1 ) reset $end
$var reg 3 * selAlu [2:0] $end
$scope module ej2 $end
$var wire 1 % ENAccu $end
$var wire 1 & ENBusIn $end
$var wire 1 ' ENBusOut $end
$var wire 4 + INBUS [3:0] $end
$var wire 1 $ clk $end
$var wire 1 ) reset $end
$var wire 3 , selectorALU [2:0] $end
$var wire 4 - data_bus [3:0] $end
$var wire 4 . SALBUSOut [3:0] $end
$var wire 2 / CZ [1:0] $end
$var wire 4 0 Acum [3:0] $end
$var wire 4 1 ALUOUT [3:0] $end
$scope module BUSIN $end
$var wire 4 2 D [3:0] $end
$var wire 1 & enable $end
$var wire 4 3 Y [3:0] $end
$upscope $end
$scope module BUSOUT $end
$var wire 1 ' enable $end
$var wire 4 4 Y [3:0] $end
$var wire 4 5 D [3:0] $end
$upscope $end
$scope module acumulador $end
$var wire 1 $ clk $end
$var wire 1 % enable $end
$var wire 1 ) reset $end
$var wire 4 6 D [3:0] $end
$var reg 4 7 Y [3:0] $end
$upscope $end
$scope module operaciones $end
$var wire 4 8 A [3:0] $end
$var wire 4 9 B [3:0] $end
$var wire 4 : Y [3:0] $end
$var wire 3 ; selector [2:0] $end
$var reg 1 < C $end
$var reg 4 = RESalu [3:0] $end
$var reg 1 > ZERO $end
$var reg 5 ? carry [4:0] $end
$upscope $end
$upscope $end
$upscope $end
$enddefinitions $end
#0
$dumpvars
bx ?
1>
b0 =
0<
b0 ;
b0 :
bz 9
b0 8
b0 7
b0 6
b0 5
bz 4
bz 3
b11 2
b0 1
b0 0
b1 /
bz .
bz -
b0 ,
b11 +
b0 *
1)
b11 (
0'
0&
0%
0$
b0 #
bz "
b1 !
$end
#1
0)
1$
#2
b0 !
b0 /
0>
bz 1
bz 5
bz 6
bz :
bz =
b10 *
b10 ,
b10 ;
1%
0$
#3
bz #
bz 0
bz 7
bz 8
1$
#4
b11 1
b11 5
b11 6
b11 :
b11 =
b11 -
b11 3
b11 9
0$
1&
#5
b11 #
b11 0
b11 7
b11 8
1$
#6
b1010 1
b1010 5
b1010 6
b1010 :
b1010 =
b1010 -
b1010 3
b1010 9
b1010 "
b1010 .
b1010 4
0$
b1010 (
b1010 +
b1010 2
0%
1'
#7
b1101 "
b1101 .
b1101 4
b1101 1
b1101 5
b1101 6
b1101 :
b1101 =
1$
b100 *
b100 ,
b100 ;
#8
0$
#9
b1101 ?
1$
b11 *
b11 ,
b11 ;
#10
0$
#11
b11 "
b11 .
b11 4
b11 1
b11 5
b11 6
b11 :
b11 =
1$
b0 *
b0 ,
b0 ;
#12
0$
#13
b1001 "
b1001 .
b1001 4
b10 !
b10 /
1<
b11001 ?
b1001 1
b1001 5
b1001 6
b1001 :
b1001 =
1$
b1 *
b1 ,
b1 ;
#14
0$
#15
1$
#16
0$
#17
1$
#18
0$
#19
1$
#20
0$
#21
1$
#22
b1100 "
b1100 .
b1100 4
b1100 1
b1100 5
b1100 6
b1100 :
b1100 =
b1100 -
b1100 3
b1100 9
0$
1%
b10 *
b10 ,
b10 ;
b1100 (
b1100 +
b1100 2
#23
b1100 #
b1100 0
b1100 7
b1100 8
1$
#24
0$
0%
#25
1$
#26
b0 "
b0 .
b0 4
0<
b1 !
b1 /
1>
b0 ?
b0 1
b0 5
b0 6
b0 :
b0 =
0$
b1 *
b1 ,
b1 ;
#27
1$
#28
b1001 "
b1001 .
b1001 4
b0 !
b0 /
0>
b1001 ?
b1001 1
b1001 5
b1001 6
b1001 :
b1001 =
b11 -
b11 3
b11 9
0$
1%
b11 (
b11 +
b11 2
#29
b110 "
b110 .
b110 4
b110 ?
b110 1
b110 5
b110 6
b110 :
b110 =
b1001 #
b1001 0
b1001 7
b1001 8
1$
#30
0$
0%
