Laboratorio#9/Ej3/JKflop.v
//Jose Luis Alvarez Pineda
//19392
//Seccion 21
//Laboratorio #9 implementacion de un FF tipo JK con un FF tipo D

module Dflop(
  input wire clk,reset,enable,D,
  output reg Y);

  always @ (posedge clk, posedge reset) begin
    if (reset == 1) Y <= 0;
    else if(enable == 1) Y <= D;
    else Y <= Y;
  end

endmodule

module JKflop(
    input wire clk,reset,enable,J,K,
    output wire Y);

    wire D;

    Dflop FFD(clk,reset,enable,D,Y);

    assign D = (~K & Y) | (J & ~Y);

endmodule

Laboratorio#9/Ej3/JKflop_tb.v
module testbench();
reg clk,reset,enable,J,K;
wire Y;

JKflop JKFF(clk,reset,enable,J,K,Y);

initial begin
clk = 0;
forever #1 clk = ~clk;
end

initial begin
reset = 1; J = 0; K = 0; enable = 0;
#1 reset = 0; enable = 1;
#3 J = 1; K = 0;
#6 J = 0; K = 1;
#6 J = 1; K = 1;
#6 J = 0; K = 0;
#6 enable = 0;
#2 J = 1; K = 0;
#2 J = 1; K = 1;
#6 reset = 1;
#1 reset = 0;
end

initial begin
#100 $finish;
end

initial begin
$dumpfile("JKflop_tb.vcd");
$dumpvars(0, testbench);
end

endmodule

Laboratorio#9/Ej3/JKflop_tb.vcd
$date
	Thu Oct 29 13:07:05 2020
$end
$version
	Icarus Verilog
$end
$timescale
	1ps
$end
$scope module testbench $end
$var wire 1 ! Y $end
$var reg 1 " J $end
$var reg 1 # K $end
$var reg 1 $ clk $end
$var reg 1 % enable $end
$var reg 1 & reset $end
$scope module JKFF $end
$var wire 1 ' D $end
$var wire 1 " J $end
$var wire 1 # K $end
$var wire 1 $ clk $end
$var wire 1 % enable $end
$var wire 1 & reset $end
$var wire 1 ! Y $end
$scope module FFD $end
$var wire 1 ' D $end
$var wire 1 $ clk $end
$var wire 1 % enable $end
$var wire 1 & reset $end
$var reg 1 ! Y $end
$upscope $end
$upscope $end
$upscope $end
$enddefinitions $end
#0
$dumpvars
0'
1&
0%
0$
0#
0"
0!
$end
#1
1%
0&
1$
#2
0$
#3
1$
#4
1'
0$
1"
#5
1!
1$
#6
0$
#7
1$
#8
0$
#9
1$
#10
0'
0$
1#
0"
#11
0!
1$
#12
0$
#13
1$
#14
0$
#15
1$
#16
1'
0$
1"
#17
0'
1!
1$
#18
0$
#19
1'
0!
1$
#20
0$
#21
0'
1!
1$
#22
1'
0$
0#
0"
#23
1$
#24
0$
#25
1$
#26
0$
#27
1$
#28
0$
0%
#29
1$
#30
0$
1"
#31
1$
#32
0'
0$
1#
#33
1$
#34
0$
#35
1$
#36
0$
#37
1$
#38
1'
0!
0$
1&
#39
1$
0&
