Laboratorio#4/AlarmaCasera/AlarmaCasera_GateLevel/Alarma_Casera_K/AlamK.v
///////////////////////////////////////////////////////////////////////////////
///Jose Luis Alvarez Pineda
///19392
///Ingenieria mecatronica
///Electronica digital
///////////////////////////////////////////////////////////////////////////////
module AlamK();
/*
Karnaugh de la alarma de casa casera.
*/
  reg A, B, C;
  wire NB, NC, out, lin1, lin2;

  not neg2(NB,B);
  not neg3(NC,C);
  and mult1(lin1,A,NB);
  and mult2(lin2,A,C);
  or sumfin(out,lin1,lin2);

//Para probar la salida que tendran las compuertas
  initial begin
    $display("A| B| C| A|");
    $display("-----------");
    $monitor("%b| %b| %b| %b|", A, B, C, out);
    A=0; B=0; C=0;
    #1 A=0; B=0; C=1;
    #1 A=0; B=1; C=0;
    #1 A=0; B=1; C=1;
    #1 A=1; B=0; C=0;
    #1 A=1; B=0; C=1;
    #1 A=1; B=1; C=0;
    #1 A=1; B=1; C=1;
    #1 $finish;
  end

//utilizado para GTKwave
  initial begin
  $dumpfile("AlamK_tb.vcd");
  $dumpvars(0,AlamK);
  end

endmodule

Laboratorio#4/AlarmaCasera/AlarmaCasera_GateLevel/Alarma_Casera_K/AlamK_tb.vcd
$date
	Thu Aug 06 20:31:57 2020
$end
$version
	Icarus Verilog
$end
$timescale
	1ps
$end
$scope module AlamK $end
$var wire 1 ! NB $end
$var wire 1 " NC $end
$var wire 1 # lin1 $end
$var wire 1 $ lin2 $end
$var wire 1 % out $end
$var reg 1 & A $end
$var reg 1 ' B $end
$var reg 1 ( C $end
$upscope $end
$enddefinitions $end
#0
$dumpvars
0(
0'
0&
0%
0$
0#
1"
1!
$end
#1
0"
1(
#2
1"
0!
0(
1'
#3
0"
1(
#4
1%
1#
1"
1!
0(
0'
1&
#5
1$
0"
1(
#6
0%
0#
0$
1"
0!
0(
1'
#7
1%
1$
0"
1(
