Laboratorio#9/Ej1/FFtipoD.v
//Jose Luis Alvarez Pineda
//19392
//Seccion 21
//Laboratorio #9: Ejercicio de FF tipo D 1 bit, 2 bits y 4 bits.

module Dflop(
  input wire clk,reset,enable,D,
  output reg Y);

  always @ (posedge clk, posedge reset) begin
    if (reset == 1) Y <= 0;
    else if(enable == 1) Y <= D;
    else Y <= Y;
  end

endmodule

module Dflop2b(
  input wire clk,reset,enable,
  input wire[1:0] D,
  output wire[1:0] Y);

  Dflop bit1(clk,reset,enable,D[0],Y[0]);
  Dflop bit2(clk,reset,enable,D[1],Y[1]);

endmodule

module Dflop4b(
  input wire clk, reset,enable,
  input wire [3:0] D,
  output wire [3:0] Y);

  Dflop bit1(clk,reset,enable,D[0],Y[0]);
  Dflop bit2(clk,reset,enable,D[1],Y[1]);
  Dflop bit3(clk,reset,enable,D[2],Y[2]);
  Dflop bit4(clk,reset,enable,D[3],Y[3]);

endmodule

Laboratorio#9/Ej1/FFtipoD_tb.v
module testbench();
reg D1,clk,reset,enable;
reg[1:0] D2;
reg[3:0] D4;
wire Y1;
wire[1:0] Y2;
wire[3:0] Y4;

Dflop FF1B(clk,reset,enable,D1,Y1);
Dflop2b FF2B(clk,reset,enable,D2,Y2);
Dflop4b FF4B(clk,reset,enable,D4,Y4);

initial begin
clk = 0;
  forever #1 clk = ~clk;
end

initial begin
//Prueba FF de 1 bit
#1 reset = 1; enable = 0; D1 = 0; D2 = 0; D4 = 0;
#1 reset = 0; D1 = 1;
#4 enable = 1;
#2 D1 = 0;

//Prueba FF de 2 bits
#1 reset = 1; enable = 0; D2 = 2'b11;
#1 reset = 0;
#2 enable = 1;
#4 D2 = 2'b10;
#4 D2 = 2'b01;
#2 enable = 0;
#2 D2 = 2'b00;
#2 D2 = 2'b11;

//prueba de FF de 4 bits
#1 reset = 1; enable = 0; D4 = 4'b0011;
#1 reset = 0;
#4 enable = 1;
#4 D4 = 4'b0110;
#4 D4 = 4'b1010;
#4 D4 = 4'b1111;
#4 D4 = 4'b1100;
#2 enable = 0;
#4 D4 = 4'b0110;
#4 D4 = 4'b1010;
#4 D4 = 4'b1111;

end

initial begin
#100 $finish;
end

initial begin
$dumpfile("FFtipoD_tb.vcd");
$dumpvars(0, testbench);
end

endmodule

Laboratorio#9/Ej1/FFtipoD_tb.vcd
$date
	Thu Oct 29 11:39:23 2020
$end
$version
	Icarus Verilog
$end
$timescale
	1ps
$end
$scope module testbench $end
$var wire 4 ! Y4 [3:0] $end
$var wire 2 " Y2 [1:0] $end
$var wire 1 # Y1 $end
$var reg 1 $ D1 $end
$var reg 2 % D2 [1:0] $end
$var reg 4 & D4 [3:0] $end
$var reg 1 ' clk $end
$var reg 1 ( enable $end
$var reg 1 ) reset $end
$scope module FF1B $end
$var wire 1 $ D $end
$var wire 1 ' clk $end
$var wire 1 ( enable $end
$var wire 1 ) reset $end
$var reg 1 # Y $end
$upscope $end
$scope module FF2B $end
$var wire 2 * D [1:0] $end
$var wire 1 ' clk $end
$var wire 1 ( enable $end
$var wire 1 ) reset $end
$var wire 2 + Y [1:0] $end
$scope module bit1 $end
$var wire 1 , D $end
$var wire 1 ' clk $end
$var wire 1 ( enable $end
$var wire 1 ) reset $end
$var reg 1 - Y $end
$upscope $end
$scope module bit2 $end
$var wire 1 . D $end
$var wire 1 ' clk $end
$var wire 1 ( enable $end
$var wire 1 ) reset $end
$var reg 1 / Y $end
$upscope $end
$upscope $end
$scope module FF4B $end
$var wire 4 0 D [3:0] $end
$var wire 1 ' clk $end
$var wire 1 ( enable $end
$var wire 1 ) reset $end
$var wire 4 1 Y [3:0] $end
$scope module bit1 $end
$var wire 1 2 D $end
$var wire 1 ' clk $end
$var wire 1 ( enable $end
$var wire 1 ) reset $end
$var reg 1 3 Y $end
$upscope $end
$scope module bit2 $end
$var wire 1 4 D $end
$var wire 1 ' clk $end
$var wire 1 ( enable $end
$var wire 1 ) reset $end
$var reg 1 5 Y $end
$upscope $end
$scope module bit3 $end
$var wire 1 6 D $end
$var wire 1 ' clk $end
$var wire 1 ( enable $end
$var wire 1 ) reset $end
$var reg 1 7 Y $end
$upscope $end
$scope module bit4 $end
$var wire 1 8 D $end
$var wire 1 ' clk $end
$var wire 1 ( enable $end
$var wire 1 ) reset $end
$var reg 1 9 Y $end
$upscope $end
$upscope $end
$upscope $end
$enddefinitions $end
#0
$dumpvars
x9
x8
x7
x6
x5
x4
x3
x2
bx 1
bx 0
x/
x.
x-
x,
bx +
bx *
x)
x(
0'
bx &
bx %
x$
x#
bx "
bx !
$end
#1
0#
0-
b0 "
b0 +
0/
03
05
07
b0 !
b0 1
09
02
04
06
08
0,
0.
b0 &
b0 0
b0 %
b0 *
0$
0(
1)
1'
#2
1$
0)
0'
#3
1'
#4
0'
#5
1'
#6
0'
1(
#7
1#
1'
#8
0'
0$
#9
0#
1,
1.
1'
b11 %
b11 *
0(
1)
#10
0'
0)
#11
1'
#12
0'
1(
#13
1-
b11 "
b11 +
1/
1'
#14
0'
#15
1'
#16
0,
0'
b10 %
b10 *
#17
b10 "
b10 +
0-
1'
#18
0'
#19
1'
#20
1,
0.
0'
b1 %
b1 *
#21
1-
b1 "
b1 +
0/
1'
#22
0'
0(
#23
1'
#24
0,
0'
b0 %
b0 *
#25
1'
#26
1,
1.
0'
b11 %
b11 *
#27
b0 "
b0 +
0-
12
14
1'
b11 &
b11 0
1)
#28
0'
0)
#29
1'
#30
0'
#31
1'
#32
0'
1(
#33
1-
b11 "
b11 +
1/
13
b11 !
b11 1
15
1'
#34
0'
#35
1'
#36
02
16
0'
b110 &
b110 0
#37
03
b110 !
b110 1
17
1'
#38
0'
#39
1'
#40
06
18
0'
b1010 &
b1010 0
#41
07
b1010 !
b1010 1
19
1'
#42
0'
#43
1'
#44
12
16
0'
b1111 &
b1111 0
#45
13
b1111 !
b1111 1
17
1'
#46
0'
#47
1'
#48
02
04
0'
b1100 &
b1100 0
#49
03
b1100 !
b1100 1
05
1'
#50
0'
0(
#51
1'
#52
0'
#53
1'
#54
14
08
0'
b110 &
b110 0
#55
1'
#56
0'
#57
1'
#58
06
18
0'
b1010 &
b1010 0
#59
1'
#60
0'
#61
1'
#62
12
16
0'
b1111 &
b1111 0
