Laboratorio#8/Memoria/ROM.v
module ROM (
  input wire [0:4095] direccion, //entrada de direccion, para seleccionar localidad
  output wire [7:0] salida //salida para dar los datos de localidad
  );

//registro de 4K X 8 (12 bits X 8 bits)
reg [7:0] memoria[0:4095];

//para leer la memoria en binario ante cada fila
initial begin
  $readmemb("MemROM.txt", memoria);
end

//asignar a la salida el valor de la memoria en esa localidad
assign salida = memoria[direccion];

endmodule

Laboratorio#8/Memoria/ROM_tb.v
module testbench();
reg [0:4095]address; //para seleccionar la localidad
wire [7:0] sal; //salida de la direccion

//crear la memoria
ROM memoria (address,sal);

//para sltar en las direcciones y leerlas en orden
initial begin
address = 0;
forever #1 address = address + 1;
end

//terminar el bucle
initial begin
#100 $finish;
end

//guardar los archivos y desplegar en GTKWAVE
initial begin
$dumpfile("ROM_tb.vcd");
$dumpvars(0, testbench);
end

endmodule

Laboratorio#8/Memoria/ROM_tb.vcd
$date
	Thu Oct 22 15:14:39 2020
$end
$version
	Icarus Verilog
$end
$timescale
	1ps
$end
$scope module testbench $end
$var wire 8 ! sal [7:0] $end
$var reg 4096 " address [0:4095] $end
$scope module memoria $end
$var wire 4096 # direccion [0:4095] $end
$var wire 8 $ salida [7:0] $end
$upscope $end
$upscope $end
$enddefinitions $end
#0
$dumpvars
b0 $
b0 #
b0 "
b0 !
$end
#1
b10010011 !
b10010011 $
b1 "
b1 #
#2
b10001110 !
b10001110 $
b10 "
b10 #
#3
b1000111 !
b1000111 $
b11 "
b11 #
#4
b1111 !
b1111 $
b100 "
b100 #
#5
b1010101 !
b1010101 $
b101 "
b101 #
#6
b1010000 !
b1010000 $
b110 "
b110 #
#7
b1010111 !
b1010111 $
b111 "
b111 #
#8
b10101001 !
b10101001 $
b1000 "
b1000 #
#9
b11001111 !
b11001111 $
b1001 "
b1001 #
#10
b11001011 !
b11001011 $
b1010 "
b1010 #
#11
b10111111 !
b10111111 $
b1011 "
b1011 #
#12
b10111101 !
b10111101 $
b1100 "
b1100 #
#13
b10101010 !
b10101010 $
b1101 "
b1101 #
#14
b10111110 !
b10111110 $
b1110 "
b1110 #
#15
bx !
bx $
b1111 "
b1111 #
#16
b10000 "
b10000 #
#17
b10001 "
b10001 #
#18
b10010 "
b10010 #
#19
b10011 "
b10011 #
#20
b10100 "
b10100 #
#21
b10101 "
b10101 #
#22
b10110 "
b10110 #
#23
b10111 "
b10111 #
#24
b11000 "
b11000 #
#25
b11001 "
b11001 #
#26
b11010 "
b11010 #
#27
b11011 "
b11011 #
#28
b11100 "
b11100 #
#29
b11101 "
b11101 #
#30
b11110 "
b11110 #
#31
b11111 "
b11111 #
#32
b100000 "
b100000 #
#33
b100001 "
b100001 #
#34
b100010 "
b100010 #
#35
b100011 "
b100011 #
#36
b100100 "
b100100 #
#37
b100101 "
b100101 #
#38
b100110 "
b100110 #
#39
b100111 "
b100111 #
#40
b101000 "
b101000 #
#41
b101001 "
b101001 #
#42
b101010 "
b101010 #
#43
b101011 "
b101011 #
#44
b101100 "
b101100 #
#45
b101101 "
b101101 #
#46
b101110 "
b101110 #
#47
b101111 "
b101111 #
#48
b110000 "
b110000 #
#49
b110001 "
b110001 #
#50
b110010 "
b110010 #
#51
b110011 "
b110011 #
#52
b110100 "
b110100 #
#53
b110101 "
b110101 #
#54
b110110 "
b110110 #
#55
b110111 "
b110111 #
#56
b111000 "
b111000 #
#57
b111001 "
b111001 #
#58
b111010 "
b111010 #
#59
b111011 "
b111011 #
#60
b111100 "
b111100 #
#61
b111101 "
b111101 #
#62
b111110 "
b111110 #
#63
b111111 "
b111111 #
#64
b1000000 "
b1000000 #
#65
b1000001 "
b1000001 #
#66
b1000010 "
b1000010 #
#67
b1000011 "
b1000011 #
#68
b1000100 "
b1000100 #
#69
b1000101 "
b1000101 #
#70
b1000110 "
b1000110 #
#71
b1000111 "
b1000111 #
#72
b1001000 "
b1001000 #
#73
b1001001 "
b1001001 #
#74
b1001010 "
b1001010 #
#75
b1001011 "
b1001011 #
#76
b1001100 "
b1001100 #
#77
b1001101 "
b1001101 #
#78
b1001110 "
b1001110 #
#79
b1001111 "
b1001111 #
#80
b1010000 "
b1010000 #
#81
b1010001 "
b1010001 #
#82
b1010010 "
b1010010 #
#83
b1010011 "
b1010011 #
#84
b1010100 "
b1010100 #
#85
b1010101 "
b1010101 #
#86
b1010110 "
b1010110 #
#87
b1010111 "
b1010111 #
#88
b1011000 "
b1011000 #
#89
b1011001 "
b1011001 #
#90
b1011010 "
b1011010 #
#91
b1011011 "
b1011011 #
#92
b1011100 "
b1011100 #
#93
b1011101 "
b1011101 #
#94
b1011110 "
b1011110 #
#95
b1011111 "
b1011111 #
#96
b1100000 "
b1100000 #
#97
b1100001 "
b1100001 #
#98
b1100010 "
b1100010 #
#99
b1100011 "
b1100011 #
#100
b1100100 "
b1100100 #
