Laboratorio#3/Ejercicio_03_SOP/LAB03_SOP.v
module LAB03_SOP();

// SOP de la tabla03 del laboratorio 3

  reg A, B, C, D;
  wire NA, NB, NC, ND, w1, w2, w3, w4, w5, w6, w7, out;


  not s1(NA,A); //(salida, entradas)
  not s2(NB,B);
  not s3(NC,C);
  not s4(ND,D);
  and mult1(w1,NA,NB,NC,ND);
  and mult2(w2,NA,NB,NC,D);
  and mult3(w3,NA,NB,C,ND);
  and mult4(w4,NA,NB,C,D);
  and mult5(w5,A,NB,NC,ND);
  and mult6(w6,A,NB,C,ND);
  and mult7(w7,A,B,C,ND);
  or sum1(out,w1,w2,w3,w4,w5,w6,w7);

  initial begin
    $display("A B C D| Y");
    $display("----------");

    $monitor("%b %b %b %b| %b", A, B, C, D, out);
    A = 0; B = 0; C=0; D=0;
    #1 A = 0; B = 0; C = 0; D = 0;
    #1 A = 0; B = 0; C = 0; D = 1;
    #1 A = 0; B = 0; C = 1; D = 0;
    #1 A = 0; B = 0; C = 1; D = 1;
    #1 A = 0; B = 1; C = 0; D = 0;
    #1 A = 0; B = 1; C = 0; D = 1;
    #1 A = 0; B = 1; C = 1; D = 0;
    #1 A = 0; B = 1; C = 1; D = 1;
    #1 A = 1; B = 0; C = 0; D = 0;
    #1 A = 1; B = 0; C = 0; D = 1;
    #1 A = 1; B = 0; C = 1; D = 0;
    #1 A = 1; B = 0; C = 1; D = 1;
    #1 A = 1; B = 1; C = 0; D = 0;
    #1 A = 1; B = 1; C = 0; D = 1;
    #1 A = 1; B = 1; C = 1; D = 0;
    #1 A = 1; B = 1; C = 1; D = 1;
    #1 $finish;
  end

  initial
    begin
      $dumpfile("LAB03_SOP_tb.vcd");
      $dumpvars(0, LAB03_SOP);
    end

endmodule

Laboratorio#3/Ejercicio_03_SOP/LAB03_SOP_tb.vcd
$date
	Thu Jul 30 15:48:46 2020
$end
$version
	Icarus Verilog
$end
$timescale
	1ps
$end
$scope module LAB03_SOP $end
$var wire 1 ! NA $end
$var wire 1 " NB $end
$var wire 1 # NC $end
$var wire 1 $ ND $end
$var wire 1 % out $end
$var wire 1 & w1 $end
$var wire 1 ' w2 $end
$var wire 1 ( w3 $end
$var wire 1 ) w4 $end
$var wire 1 * w5 $end
$var wire 1 + w6 $end
$var wire 1 , w7 $end
$var reg 1 - A $end
$var reg 1 . B $end
$var reg 1 / C $end
$var reg 1 0 D $end
$upscope $end
$enddefinitions $end
#0
$dumpvars
00
0/
0.
0-
0,
0+
0*
0)
0(
0'
1&
1%
1$
1#
1"
1!
$end
#2
0&
1'
0$
10
#3
1(
0'
1$
0#
00
1/
#4
0(
1)
0$
10
#5
0%
1$
0)
1#
0"
00
0/
1.
#6
0$
10
#7
1$
0#
00
1/
#8
0$
10
#9
1%
1*
1$
1#
1"
0!
00
0/
0.
1-
#10
0%
0*
0$
10
#11
1%
1+
1$
0#
00
1/
#12
0%
0+
0$
10
#13
1$
1#
0"
00
0/
1.
#14
0$
10
#15
1%
1,
1$
0#
00
1/
#16
0%
0,
0$
10
