Laboratorio#3/Ejercicio_02_SOP/LAB02_SOP.v
module LAB02_SOP();

// SOP de la tabla02 del laboratorio 3

  reg A, B, C;
  wire NA, NB, NC, w1, w2, w3, out;


  not s1(NA,A); //(salida, entradas)
  not s2(NB,B);
  not s3(NC,C);
  and mult1(w1,NA,NB,C);
  and mult2(w2,A,B,NC);
  and mult3(w3,A,B,C);
  or sum1(out,w1,w2,w3);

  initial begin
    $display("A B C| Y");
    $display("-------");

    $monitor("%b %b %b| %b", A, B, C, out);
    A = 0; B = 0; C=0;
    #1 A = 0; B = 0; C=1;
    #1 A = 0; B = 1; C=0;
    #1 A = 0; B = 1; C=1;
    #1 A = 1; B = 0; C=0;
    #1 A = 1; B = 0; C=1;
    #1 A = 1; B = 1; C=0;
    #1 A = 1; B = 1; C=1;
    #5 $finish;
  end

  initial
    begin
      $dumpfile("LAB02_SOP_tb.vcd");
      $dumpvars(0, LAB02_SOP);
    end

endmodule

Laboratorio#3/Ejercicio_02_SOP/LAB02_SOP_tb.vcd
$date
	Thu Jul 30 15:43:14 2020
$end
$version
	Icarus Verilog
$end
$timescale
	1ps
$end
$scope module LAB02_SOP $end
$var wire 1 ! NA $end
$var wire 1 " NB $end
$var wire 1 # NC $end
$var wire 1 $ out $end
$var wire 1 % w1 $end
$var wire 1 & w2 $end
$var wire 1 ' w3 $end
$var reg 1 ( A $end
$var reg 1 ) B $end
$var reg 1 * C $end
$upscope $end
$enddefinitions $end
#0
$dumpvars
0*
0)
0(
0'
0&
0%
0$
1#
1"
1!
$end
#1
1$
1%
0#
1*
#2
0$
0%
1#
0"
0*
1)
#3
0#
1*
#4
1#
1"
0!
0*
0)
1(
#5
0#
1*
#6
1$
1&
1#
0"
0*
1)
#7
0&
1'
0#
1*
