PROYECTO#1-FSM/ScriptsDelProyecto/UnionFSM/FSMJ.v
///////////////////////////////////////////////////////////////////////////////
///Jose Luis Alvarez Pineda
///19392
///Electronica digital
///Proyecto 1
///FSM´s en conjunto
///union de todas las FSM y adicion del timmer
///////////////////////////////////////////////////////////////////////////////

//implementacion de un FF con solo reset asincrono y es del tipo D
module Dflop(
  input wire areset, clk,
  input wire [3:0] D,
  output reg [3:0] Y);

    always @ ( posedge clk, posedge areset) begin
      if (areset) Y <= 4'b0000;
      else Y <= D;
    end

endmodule
///////////////////////////////////////////////////////////////////////////////
///
///TIMMERS
///////////////////////////////////////////////////////////////////////////////
module timmerA(
  input wire CLK,
  input wire RESET,
  input wire [1:0] M,
  output reg Y,
  output reg[2:0] count);

  reg[2:0] tiempo = 3'b000;
  reg permit = 1;

always @ ( posedge CLK, M[1], M[0], RESET) begin

if(RESET == 1)begin
  tiempo <= 3'b000;
  Y <= 0;
  permit <= 1;
end

  if(CLK == 1)begin


      if((M[1] == 1) & (permit == 1))begin
        tiempo <= tiempo + 3'b001;
        Y <= 0;
      end

      else if((M[0] == 1) & (permit == 1))begin
        tiempo <= tiempo + 3'b001;
        Y <= 0;
      end

      if (tiempo == 3'b101)begin
        Y <= 1;
        permit <= 0;
      end

      count <= tiempo;
  end
end

endmodule

module timmerB(
  input wire CLK,
  input wire RESET,
  input wire [1:0] M,
  output reg Y,
  output reg[2:0] count);

  reg[2:0] tiempo = 3'b000;
  reg permit = 1;

always @ ( posedge CLK, M[1], M[0], RESET) begin

if(RESET == 1)begin
  tiempo <= 3'b000;
  Y <= 0;
  permit <= 1;
end

  if(CLK == 1)begin

      if((M[1] == 1) & (permit == 1))begin
        tiempo <= tiempo + 3'b001;
        Y <= 0;
      end

      else if((M[0] == 1) & (permit == 1))begin
        tiempo <= tiempo + 3'b001;
        Y <= 0;
      end

      if (tiempo == 3'b110)begin
        Y <= 1;
        permit <= 0;
      end

      count <= tiempo;
  end
end

endmodule

module timmerC(
  input wire CLK,
  input wire RESET,
  input wire M,
  output reg Y,
  output reg[2:0] count);

  reg[2:0] tiempo = 3'b000;
  reg permit = 1;

always @ ( posedge CLK, M, RESET) begin

if(RESET == 1)begin
  tiempo <= 3'b000;
  Y <= 0;
  permit <= 1;
end

  if(CLK == 1)begin

      if((M == 1) & (permit == 1))begin
        tiempo <= tiempo + 3'b001;
        Y <= 0;
      end

      if (tiempo == 3'b011)begin
        Y <= 1;
        permit <= 0;
      end

      count <= tiempo;
  end
end

endmodule

///////////////////////////////////////////////////////////////////////////////
///
///MAQUINA DISPENSADORA
////////////////////////////////////////////////////////////////////////////////
module FSMdisp(
  input wire RESET, CLK,
  input wire E, A, B, C,
  input wire [3:0] SA,
  input wire [2:0] CIN,
  output wire [1:0] M1,
  output wire [1:0] M2,
  output wire M3,Li,
  output wire [2:0] IND,
  output wire [3:0]S,
  output wire [3:0]Sf);

  Dflop FF1estado (RESET, CLK, Sf, S);

//estados futuros de la maquina de dispensar
assign Sf[3] = (S[3] & ~S[2] & ~S[1]) | (~S[3] & S[2] & S[1] & ~S[0] & SA[2]);

assign Sf[2] = (~S[3] & S[2] & ~S[1]) | (~S[3] & S[1] & S[0]) | (~S[3] & S[2] & ~SA[2]);

assign Sf[1] = (~S[3] & S[2] & S[1] & S[0]) | (~S[3] & ~S[2] & S[1] & ~S[0]) |
                (~S[3] & S[2] & ~S[1] & B) | (~S[3] & ~S[2] & ~S[1] & S[0] & A) |
                (~S[3] & ~S[2] & ~S[0] & SA[3] & ~SA[2] & SA[0] & CIN[2] & CIN[1] & E) |
                (~S[3] & ~S[2] & ~S[0] & SA[3] & SA[0] & CIN[2] & CIN[1] & CIN[0] & E) |
                (~S[3] & S[1] & ~S[0] & ~SA[2]);

assign Sf[0] = (~S[2] & ~S[1] & S[0]) | (~S[3] & S[2] & S[1] & S[0]) | (~S[3] & S[2] & S[1] & ~SA[2]) |
                (S[3] & ~S[2] & ~S[1] & C) | (~S[3] & ~S[2] & S[1] & ~S[0] & A) |
                (~S[3] & ~S[2] & ~S[1] & SA[3] & ~SA[2] & ~SA[0] & CIN[2] & CIN[1] & E) |
                (~S[3] & ~S[2] & ~S[1] & SA[3] & ~SA[0] & CIN[2] & CIN[1] & CIN[0] & E) |
                (~S[3] & S[1] & S[0] & SA[1]) | (~S[3] & ~S[1] & S[0] & ~B) ;
//salidas de la maquina de dispensar
assign M1[1] = ~S[3] & ~S[2] & S[1] & ~S[0];

assign M1[0] = ~S[3] & ~S[2] & ~S[1] & S[0];

assign M2[1] = ~S[3] & S[2] & ~S[1] & S[0];

assign M2[0] = ~S[3] & S[2] & ~S[1] & ~S[0];

assign M3 = S[3] & ~S[2] & ~S[1] & ~S[0];

assign Li = (~S[3] & S[2] & S[1] & S[0]) | (S[3] & ~S[2] & ~S[1] & S[0]);

assign IND[2] = (~S[3] & S[2] & S[1]) | (S[3] & ~S[2] & ~S[1]) | (~S[3] & S[2] & S[0]) | (~S[3] & S[1] & S[0]);

assign IND[1] = (~S[3] & S[1]) | (~S[3] & S[2] & ~S[0]) | (S[3] & ~S[2] & ~S[1] & S[0]);

assign IND[0] = (S[3] & ~S[2] & ~S[1]) | (~S[3] & S[2] & ~S[0]) | (~S[3] & ~S[2] & S[0]) | (~S[3] & S[1] & S[0]);

endmodule
///////////////////////////////////////////////////////////////////////////////
///
///MAQUINA SELECTORA
///////////////////////////////////////////////////////////////////////////////
module SFMSelector(
  input areset,clk,
  input wire C,T,L,A,N,V,
  output wire [3:0]S,
  output wire [3:0]Sf,
  output wire [3:0]SA);

 Dflop FF1 (areset, clk, Sf, S);

//SON LOS ESTADOS FUTUROS INTERNOS DE LA MAQUINA
 assign Sf[3] = (S[3] & ~S[2]) | (S[3] & ~S[1]) | (S[3] & ~S[0]) |(~S[2] & ~S[1] & ~S[0] & ~C & T);

 assign Sf[2] = (~S[3] & S[2]) | (S[2] & ~S[1]) | (S[2] & ~S[0]) | (~S[3] & S[1] & ~N & V)
                | (S[1] & ~S[0] & ~N & V) | (~S[3] & S[1] & N & ~V)
                | (S[1] & ~S[0] & N & ~V) | (S[3] & ~S[1] & S[0] & ~N & V);

 assign Sf[1] = (S[2] & S[1] & ~S[0]) | (~S[3] & ~S[2] & S[0] & ~L & A) |
                (~S[3] & ~S[2] & S[0] & L & ~A) | (S[3] & ~S[2] & S[0] & N & ~V) |
                (~S[3] & S[1] & S[0]) | (S[3] & ~S[2] & S[1] & V) | (~S[2] & S[1] & N & V) |
                (~S[2] & S[1] & ~N & ~V) | (S[3] & ~S[2] & ~S[1] & ~S[0] & ~L & A) ;

 assign Sf[0] = (~S[3] & S[2] & S[0]) | (S[2] & ~S[1] & S[0]) | (~S[3] & ~S[2] & S[1] & ~N & V) |
                (S[3] & ~S[2] & S[1] & N & ~V) | (S[3] & ~S[2] & ~S[1] & ~S[0] & L & ~A) |
                | (~S[3] & ~S[1] & S[0] & ~L) | (~S[3] & ~S[1] & S[0] & A) | (S[3] & ~S[2] & S[0] & N) |
                (~S[2] & S[1] & S[0] & ~N) | (~S[2] & S[1] & S[0] & V) | (S[3] & ~S[2] & S[0] & ~V) |
                (~S[3] & ~S[2] & ~S[1] & ~S[0] & C & ~T);

//ASIGNACION DE LAS SALIDAS DEL MODULO
  assign SA[3] = S[2] | (S[3] & S[1] & S[0]);

  assign SA[2] = (~S[3] & S[2] & S[0]) | (S[3] & S[2] & ~S[0]);

  assign SA[1] = (S[2] & S[1]) | (S[3] & S[2] & S[0]) | (~S[3] & S[1] & S[0]) | (S[3] & S[1] & ~S[0]);

  assign SA[0] = S[3];

endmodule

PROYECTO#1-FSM/ScriptsDelProyecto/UnionFSM/FSMJ_tb.v
module BANCODEPRUEBA();

//variables globales para todas las maquinas
reg CLK1, CLK2;
reg RESET;
reg ResetManual;

///variables asociadas a los contadores
wire taima, taimb,taimc;
wire[2:0]counta;
wire[2:0]countb;
wire[2:0]countc;

///variables asociadas al dispensador
reg E;
wire[3:0] FuturosDispensador;
wire[3:0] ActualesDispensador;
reg [2:0] CIN;
wire [3:0] SA;
wire [1:0] M1;
wire [1:0] M2;
wire M3, Li;
wire [2:0] LCD;

//variables asociadas al selector
reg C,T,L,A,N,V;
wire [3:0]FuturosSelector;
wire [3:0]ActualesSelector;

//modulos asociados a las FMS
SFMSelector selector(RESET, CLK1, C, T, L, A, N, V, ActualesSelector, FuturosSelector, SA);
FSMdisp dispensador(RESET, CLK1, E, taima, taimb, taimc, SA, CIN, M1, M2, M3, Li, LCD, ActualesDispensador, FuturosDispensador);

//modulos asociados a los timmers
timmerA TIMA(CLK2,RESET,M1,taima, counta);
timmerB TIMB(CLK2,RESET,M2,taimb, countb);
timmerC TIMC(CLK2,RESET,M3,taimc, countc);

//logica secuencial para la asignacion de valores a un registro al momento de actualizarse
always @ ( posedge Li ,posedge ResetManual, posedge CLK1) begin
  RESET <= 0; //para que el reset se mantenga en 0 de no presionar nada

  if(Li == 1)begin//asignar el valor de LI al reset cuando se active
  RESET <= Li;
  end

  else if(ResetManual == 1) begin //asignar el valor del reset manual al reset.
  RESET <= ResetManual;
  end
end

//Clock para las FSM
initial begin
  CLK1 = 0;
  forever #1 CLK1 = ~CLK1; //cambio ininterrumpido del CLOCK durante todo el tiempo.
end

//Clock para los contadores
initial begin
  CLK2 = 0;
  forever #4 CLK2 = ~CLK2; //para cambiar el clock de forma ininterrumpida
end

initial begin
///////////////////////////////////////////////////////////////////////////////////////
///En esta parte del testbench se puede cambiar el valor de las variables para
///modificar la eleccion.
/// Se puede modificar la variable C por la T para alternar por elegir Cafe o Te
/// Se puede modificar la variable L por A para alternar en la eleccion de Leche o Agua
/// Se puede modificar la variable V por N para alternar en la eleccion sin extra
///           o con Vainilla la bebida.
/// Se puede modificar el valor de CIN para observar el comportamiento del dispensador
///           luego de la eleccion.
/// Se puede colocar desde el inicio E como 0 para observar el comportamiento del
///           dispensador.
////////////////////////////////////////////////////////////////////////////////////////
ResetManual = 1;
#1 ResetManual = 0; E = 0; C = 0; T = 0; A = 0; L = 0; N = 0; V = 0; CIN = 3'b000;
#3 C = 1;
#2 C = 0; L = 1;
#3 L = 0; V = 1;////////////////////////////////////////////////////////////////////////////////////////
#2 V = 0; CIN = 3'b111;
#3 E = 1;
#2 E = 0;
////////////////////////////////////////////////////////////////////////////////////////
end

initial begin
#500 $finish;
end

initial begin
$dumpfile ("FSMJ_tb.vcd");
$dumpvars (0, BANCODEPRUEBA);

end
endmodule

PROYECTO#1-FSM/ScriptsDelProyecto/UnionFSM/FSMJ_tb.vcd
$date
	Sun Oct 04 17:12:51 2020
$end
$version
	Icarus Verilog
$end
$timescale
	1ps
$end
$scope module BANCODEPRUEBA $end
$var wire 1 ! taimc $end
$var wire 1 " taimb $end
$var wire 1 # taima $end
$var wire 3 $ countc [2:0] $end
$var wire 3 % countb [2:0] $end
$var wire 3 & counta [2:0] $end
$var wire 4 ' SA [3:0] $end
$var wire 1 ( M3 $end
$var wire 2 ) M2 [1:0] $end
$var wire 2 * M1 [1:0] $end
$var wire 1 + Li $end
$var wire 3 , LCD [2:0] $end
$var wire 4 - FuturosSelector [3:0] $end
$var wire 4 . FuturosDispensador [3:0] $end
$var wire 4 / ActualesSelector [3:0] $end
$var wire 4 0 ActualesDispensador [3:0] $end
$var reg 1 1 A $end
$var reg 1 2 C $end
$var reg 3 3 CIN [2:0] $end
$var reg 1 4 CLK1 $end
$var reg 1 5 CLK2 $end
$var reg 1 6 E $end
$var reg 1 7 L $end
$var reg 1 8 N $end
$var reg 1 9 RESET $end
$var reg 1 : ResetManual $end
$var reg 1 ; T $end
$var reg 1 < V $end
$scope module TIMA $end
$var wire 1 5 CLK $end
$var wire 1 9 RESET $end
$var wire 2 = M [1:0] $end
$var reg 1 # Y $end
$var reg 3 > count [2:0] $end
$var reg 1 ? permit $end
$var reg 3 @ tiempo [2:0] $end
$upscope $end
$scope module TIMB $end
$var wire 1 5 CLK $end
$var wire 1 9 RESET $end
$var wire 2 A M [1:0] $end
$var reg 1 " Y $end
$var reg 3 B count [2:0] $end
$var reg 1 C permit $end
$var reg 3 D tiempo [2:0] $end
$upscope $end
$scope module TIMC $end
$var wire 1 5 CLK $end
$var wire 1 9 RESET $end
$var wire 1 ( M $end
$var reg 1 ! Y $end
$var reg 3 E count [2:0] $end
$var reg 1 F permit $end
$var reg 3 G tiempo [2:0] $end
$upscope $end
$scope module dispensador $end
$var wire 1 # A $end
$var wire 1 " B $end
$var wire 1 ! C $end
$var wire 3 H CIN [2:0] $end
$var wire 1 4 CLK $end
$var wire 1 6 E $end
$var wire 1 + Li $end
$var wire 1 ( M3 $end
$var wire 1 9 RESET $end
$var wire 4 I Sf [3:0] $end
$var wire 4 J SA [3:0] $end
$var wire 4 K S [3:0] $end
$var wire 2 L M2 [1:0] $end
$var wire 2 M M1 [1:0] $end
$var wire 3 N IND [2:0] $end
$scope module FF1estado $end
$var wire 4 O D [3:0] $end
$var wire 1 9 areset $end
$var wire 1 4 clk $end
$var reg 4 P Y [3:0] $end
$upscope $end
$upscope $end
$scope module selector $end
$var wire 1 1 A $end
$var wire 1 2 C $end
$var wire 1 7 L $end
$var wire 1 8 N $end
$var wire 1 ; T $end
$var wire 1 < V $end
$var wire 1 9 areset $end
$var wire 1 4 clk $end
$var wire 4 Q Sf [3:0] $end
$var wire 4 R SA [3:0] $end
$var wire 4 S S [3:0] $end
$scope module FF1 $end
$var wire 4 T D [3:0] $end
$var wire 1 9 areset $end
$var wire 1 4 clk $end
$var reg 4 U Y [3:0] $end
$upscope $end
$upscope $end
$upscope $end
$enddefinitions $end
#0
$dumpvars
b0 U
bx00x T
b0 S
b0 R
bx00x Q
b0 P
b0 O
b0 N
b0 M
b0 L
b0 K
b0 J
b0 I
bx H
b0 G
1F
bx E
b0 D
1C
bx B
b0 A
b0 @
1?
bx >
b0 =
x<
x;
1:
19
x8
x7
x6
05
04
bx 3
x2
x1
b0 0
b0 /
b0 .
bx00x -
b0 ,
0+
b0 *
b0 )
0(
b0 '
bx &
bx %
bx $
0#
0"
0!
$end
#1
09
b0 -
b0 Q
b0 T
b0 3
b0 H
0<
08
07
01
0;
02
06
0:
14
#2
04
#3
14
#4
b0 &
b0 >
b0 %
b0 B
b0 $
b0 E
b1 -
b1 Q
b1 T
04
12
15
#5
b1 -
b1 Q
b1 T
b1 /
b1 S
b1 U
14
#6
b10 -
b10 Q
b10 T
04
17
02
#7
b10 /
b10 S
b10 U
14
#8
04
05
#9
b101 -
b101 Q
b101 T
14
1<
07
#10
04
#11
b1100 '
b1100 J
b1100 R
b101 /
b101 S
b101 U
b101 -
b101 Q
b101 T
14
b111 3
b111 H
0<
#12
04
15
#13
14
#14
b1 .
b1 I
b1 O
04
16
#15
b1 @
b1 ,
b1 N
b1 *
b1 =
b1 M
b1 0
b1 K
b1 P
14
#16
04
06
05
#17
14
#18
04
#19
14
#20
b1 &
b1 >
b10 @
04
15
#21
14
#22
04
#23
14
#24
04
05
#25
14
#26
04
#27
14
#28
b10 &
b10 >
b11 @
04
15
#29
14
#30
04
#31
14
#32
04
05
#33
14
#34
04
#35
14
#36
b11 &
b11 >
b100 @
04
15
#37
14
#38
04
#39
14
#40
04
05
#41
14
#42
04
#43
14
#44
b100 &
b100 >
b101 @
04
15
#45
14
#46
04
#47
14
#48
04
05
#49
14
#50
04
#51
14
#52
b11 .
b11 I
b11 O
b101 &
b101 >
0?
1#
b110 @
04
15
#53
b110 &
b110 >
b100 .
b100 I
b100 O
b111 ,
b111 N
b0 *
b0 =
b0 M
b11 0
b11 K
b11 P
14
#54
04
#55
b1 D
b11 ,
b11 N
b1 )
b1 A
b1 L
b100 0
b100 K
b100 P
14
#56
04
05
#57
14
#58
04
#59
14
#60
b1 %
b1 B
b10 D
04
15
#61
14
#62
04
#63
14
#64
04
05
#65
14
#66
04
#67
14
#68
b10 %
b10 B
b11 D
04
15
#69
14
#70
04
#71
14
#72
04
05
#73
14
#74
04
#75
14
#76
b11 %
b11 B
b100 D
04
15
#77
14
#78
04
#79
14
#80
04
05
#81
14
#82
04
#83
14
#84
b100 %
b100 B
b101 D
04
15
#85
14
#86
04
#87
14
#88
04
05
#89
14
#90
04
#91
14
#92
b101 %
b101 B
b110 D
04
15
#93
14
#94
04
#95
14
#96
04
05
#97
14
#98
04
#99
14
#100
b110 .
b110 I
b110 O
b110 %
b110 B
0C
1"
b111 D
04
15
#101
b111 %
b111 B
b111 ,
b111 N
b1000 .
b1000 I
b1000 O
b0 )
b0 A
b0 L
b110 0
b110 K
b110 P
14
#102
04
#103
b1 G
b101 ,
b101 N
1(
b1000 0
b1000 K
b1000 P
14
#104
04
05
#105
14
#106
04
#107
14
#108
b1 $
b1 E
b10 G
04
15
#109
14
#110
04
#111
14
#112
04
05
#113
14
#114
04
#115
14
#116
b10 $
b10 E
b11 G
04
15
#117
14
#118
04
#119
14
#120
04
05
#121
14
#122
04
#123
14
#124
b1001 .
b1001 I
b1001 O
b11 $
b11 E
0F
1!
b100 G
04
15
#125
b0 -
b0 Q
b0 T
b0 .
b0 I
b0 O
b0 '
b0 J
b0 R
1?
0#
b0 @
1C
0"
b0 D
1F
0!
b0 G
b0 /
b0 S
b0 U
19
b100 $
b100 E
b0 ,
b0 N
0+
0(
b0 0
b0 K
b0 P
14
#126
04
#127
b0 &
b0 >
b0 %
b0 B
b0 $
b0 E
09
14
